{
  "formatVersion": 1,
  "database": {
    "version": 3,
    "identityHash": "849610bb8f97c2a078408cceebf61bd5",
    "entities": [
      {
        "tableName": "Recipe",
        "createSql": "CREATE TABLE IF NOT EXISTS `${TABLE_NAME}` (`id` INTEGER PRIMARY KEY AUTOINCREMENT NOT NULL, `name` TEXT, `category` TEXT, `ingredients` TEXT, `cookingInstructions` TEXT, `picture` BLOB)",
        "fields": [
          {
            "fieldPath": "id",
            "columnName": "id",
            "affinity": "INTEGER",
            "notNull": true
          },
          {
            "fieldPath": "name",
            "columnName": "name",
            "affinity": "TEXT",
            "notNull": false
          },
          {
            "fieldPath": "category",
            "columnName": "category",
            "affinity": "TEXT",
            "notNull": false
          },
          {
            "fieldPath": "ingredients",
            "columnName": "ingredients",
            "affinity": "TEXT",
            "notNull": false
          },
          {
            "fieldPath": "cookingInstructions",
            "columnName": "cookingInstructions",
            "affinity": "TEXT",
            "notNull": false
          },
          {
            "fieldPath": "picture",
            "columnName": "picture",
            "affinity": "BLOB",
            "notNull": false
          }
        ],
        "primaryKey": {
          "columnNames": [
            "id"
          ],
          "autoGenerate": true
        },
        "indices": [],
        "foreignKeys": []
      }
    ],
    "views": [],
    "setupQueries": [
      "CREATE TABLE IF NOT EXISTS room_master_table (id INTEGER PRIMARY KEY,identity_hash TEXT)",
      "INSERT OR REPLACE INTO room_master_table (id,identity_hash) VALUES(42, '849610bb8f97c2a078408cceebf61bd5')"
    ]
  }
}